supplychain_demo/__init__.py
supplychain_demo/cli.py
supplychain_demo_0xkratos-0.0.1.dist-info/METADATA
supplychain_demo_0xkratos-0.0.1.dist-info/WHEEL
supplychain_demo_0xkratos-0.0.1.dist-info/entry_points.txt
supplychain_demo_0xkratos-0.0.1.dist-info/top_level.txt
supplychain_demo_0xkratos-0.0.1.dist-info/RECORD
