Metadata-Version: 2.4
Name: supplychain-demo-0xkratos
Version: 0.0.1
Summary: Safe demo package to show import-time code execution (harmless)
Author: 0xkratos
License: MIT
